<annotation>
	<folder>13702_video_23_07_2022_01_00</folder>
	<filename>13702_video_23_07_2022_01_004400.jpg</filename>
	<path>/home/jotade/Desktop/Sciling/camdown/out/out_1h_Etiquetado/1h_NOCHE/23_07_2022_01_00_Videos/Frames_1H/13702_video_23_07_2022_01_00/13702_video_23_07_2022_01_004400.jpg</path>
	<source>
		<database>Unknown</database>
	</source>
	<size>
		<width>640</width>
		<height>640</height>
		<depth>3</depth>
	</size>
	<segmented>0</segmented>
	<object>
		<name>car</name>
		<pose>Unspecified</pose>
		<truncated>0</truncated>
		<difficult>0</difficult>
		<bndbox>
			<xmin>193</xmin>
			<ymin>249</ymin>
			<xmax>227</xmax>
			<ymax>276</ymax>
		</bndbox>
	</object>
	<object>
		<name>car</name>
		<pose>Unspecified</pose>
		<truncated>0</truncated>
		<difficult>0</difficult>
		<bndbox>
			<xmin>593</xmin>
			<ymin>298</ymin>
			<xmax>639</xmax>
			<ymax>319</ymax>
		</bndbox>
	</object>
</annotation>
