<annotation>
<folder>w2_LuisBolinches-Menorca</folder>
<filename>w2_LuisBolinches-Menorca1050.jpg</filename>
<path>/home/jotade/Desktop/Sciling/camdown/out/out_LAN/Frames_5min/w2_LuisBolinches-Menorca/w2_LuisBolinches-Menorca1050.jpg</path>
<source>
<database>Unknown</database>
</source>
<size>
<width>640</width>
<height>640</height>
<depth>3</depth>
</size>
<segmented>0</segmented>
<object>
<name>car</name>
<pose>Unspecified</pose>
<truncated>0</truncated>
<difficult>0</difficult>
<bndbox>
<xmin>225</xmin>
<ymin>306</ymin>
<xmax>336</xmax>
<ymax>404</ymax>
</bndbox>
</object>
<object>
<name>car</name>
<pose>Unspecified</pose>
<truncated>0</truncated>
<difficult>0</difficult>
<bndbox>
<xmin>352</xmin>
<ymin>144</ymin>
<xmax>389</xmax>
<ymax>193</ymax>
</bndbox>
</object>
<object>
<name>car</name>
<pose>Unspecified</pose>
<truncated>0</truncated>
<difficult>0</difficult>
<bndbox>
<xmin>312</xmin>
<ymin>108</ymin>
<xmax>361</xmax>
<ymax>142</ymax>
</bndbox>
</object>
<object>
<name>car</name>
<pose>Unspecified</pose>
<truncated>0</truncated>
<difficult>0</difficult>
<bndbox>
<xmin>358</xmin>
<ymin>95</ymin>
<xmax>387</xmax>
<ymax>119</ymax>
</bndbox>
</object>
<object>
<name>car</name>
<pose>Unspecified</pose>
<truncated>0</truncated>
<difficult>0</difficult>
<bndbox>
<xmin>429</xmin>
<ymin>111</ymin>
<xmax>487</xmax>
<ymax>142</ymax>
</bndbox>
</object>
<object>
<name>car</name>
<pose>Unspecified</pose>
<truncated>0</truncated>
<difficult>0</difficult>
<bndbox>
<xmin>427</xmin>
<ymin>82</ymin>
<xmax>481</xmax>
<ymax>111</ymax>
</bndbox>
</object>
<object>
<name>car</name>
<pose>Unspecified</pose>
<truncated>0</truncated>
<difficult>0</difficult>
<bndbox>
<xmin>189</xmin>
<ymin>231</ymin>
<xmax>279</xmax>
<ymax>306</ymax>
</bndbox>
</object>
<object>
<name>car</name>
<pose>Unspecified</pose>
<truncated>0</truncated>
<difficult>0</difficult>
<bndbox>
<xmin>249</xmin>
<ymin>197</ymin>
<xmax>312</xmax>
<ymax>242</ymax>
</bndbox>
</object>
<object>
<name>car</name>
<pose>Unspecified</pose>
<truncated>0</truncated>
<difficult>0</difficult>
<bndbox>
<xmin>278</xmin>
<ymin>162</ymin>
<xmax>330</xmax>
<ymax>199</ymax>
</bndbox>
</object>
<object>
<name>car</name>
<pose>Unspecified</pose>
<truncated>0</truncated>
<difficult>0</difficult>
<bndbox>
<xmin>309</xmin>
<ymin>135</ymin>
<xmax>341</xmax>
<ymax>175</ymax>
</bndbox>
</object>
<object>
<name>car</name>
<pose>Unspecified</pose>
<truncated>0</truncated>
<difficult>0</difficult>
<bndbox>
<xmin>10</xmin>
<ymin>413</ymin>
<xmax>147</xmax>
<ymax>559</ymax>
</bndbox>
</object>
</annotation>